{
  "walls": [
    {
      "id": 0,
      "p1": [
        -5.840833136794323,
        -0.12286342432365524
      ],
      "p2": [
        -3.9484165296771643,
        -0.502094378478983
      ],
      "length": 1.9300406035838678,
      "direction": [
        0.9805061114264968,
        -0.19648858860832227
      ],
      "rmse": 0.003239098120392561
    },
    {
      "id": 1,
      "p1": [
        -0.9604104785760751,
        -1.1859181293488388
      ],
      "p2": [
        1.47392654913018,
        -1.6025070351550714
      ],
      "length": 2.469725304745967,
      "direction": [
        0.9856711687837745,
        -0.16867823518885874
      ],
      "rmse": 0.017532540217925087
    },
    {
      "id": 2,
      "p1": [
        5.022876030589035,
        -2.2837637564746167
      ],
      "p2": [
        6.071033748580223,
        -2.4864672126768297
      ],
      "length": 1.067578237386289,
      "direction": [
        0.981808809213181,
        -0.18987222585042707
      ],
      "rmse": 0.004933847656923464
    },
    {
      "id": 3,
      "p1": [
        2.8067000245280105,
        4.955893747562346
      ],
      "p2": [
        1.8574110740820704,
        0.2903508250135336
      ],
      "length": 4.76113854803492,
      "direction": [
        -0.19938276125923568,
        -0.9799216879478904
      ],
      "rmse": 0.006549511389412618
    },
    {
      "id": 4,
      "p1": [
        -5.120822783124717,
        3.7477698098278336
      ],
      "p2": [
        -5.863019979862032,
        0.02642282350302394
      ],
      "length": 3.794638332104059,
      "direction": [
        -0.1955910239079461,
        -0.9806855517262612
      ],
      "rmse": 0.0027783003830209683
    }
  ],
  "metadata": {
    "input_file": "/home/qzl/Main/MobiMind/test/test_online_road/extracted_lidar_data_code/extracted_lidar_data/laserscan_json/laserscan_000025.json",
    "num_walls": 5,
    "x_limit": 10.0,
    "y_limit": 5.0,
    "params": {
      "rdp_epsilon": 0.05,
      "wall_rmse_thresh": 0.07,
      "min_wall_length": 0.8,
      "gap_thresh": 2
    }
  }
}