{
  "walls": [
    {
      "id": 0,
      "p1": [
        -7.50869275045069,
        -1.021913120845372
      ],
      "p2": [
        -7.436954654582585,
        -1.8540462527720287
      ],
      "length": 0.8352196738875636,
      "direction": [
        0.08589129077159466,
        -0.9963045147782827
      ],
      "rmse": 0.00242322080288408
    },
    {
      "id": 1,
      "p1": [
        -5.88769778106474,
        -1.7747924794379455
      ],
      "p2": [
        6.345792061388894,
        -0.6753943789101068
      ],
      "length": 12.282790802942973,
      "direction": [
        0.9959861760008353,
        0.08950719084650714
      ],
      "rmse": 0.026393797605854703
    },
    {
      "id": 2,
      "p1": [
        7.927021218293861,
        2.086316310105297
      ],
      "p2": [
        8.026499864400574,
        0.8076074737335814
      ],
      "length": 1.282572527869801,
      "direction": [
        0.07756180952342312,
        -0.9969875454093958
      ],
      "rmse": 0.006348797792715059
    },
    {
      "id": 3,
      "p1": [
        5.0374209721259575,
        1.6357643061549532
      ],
      "p2": [
        5.959571880469652,
        1.603168395357144
      ],
      "length": 0.9227268236915193,
      "direction": [
        0.9993758549833388,
        -0.035325634804211345
      ],
      "rmse": 0.025529150077029418
    },
    {
      "id": 4,
      "p1": [
        1.5114359995647968,
        1.2507095211932238
      ],
      "p2": [
        4.496969592412302,
        1.569307601889262
      ],
      "length": 3.0024848993865287,
      "direction": [
        0.9943542408671322,
        0.10611146812455777
      ],
      "rmse": 0.06023500624983
    }
  ],
  "metadata": {
    "input_file": "/home/qzl/test_road/test_online_road/extracted_lidar_data_code/extracted_lidar_data/laserscan_json2/laserscan_000056.json",
    "num_walls": 5,
    "x_limit": 10.0,
    "y_limit": 5.0,
    "params": {
      "rdp_epsilon": 0.05,
      "wall_rmse_thresh": 0.07,
      "min_wall_length": 0.8,
      "gap_thresh": 2
    }
  }
}