{
  "walls": [
    {
      "id": 0,
      "p1": [
        -2.7506264012235246,
        -2.092137587169175
      ],
      "p2": [
        -2.709421646603531,
        -3.0445788861585514
      ],
      "length": 0.9533321875526202,
      "direction": [
        0.04322182252729002,
        -0.9990655003829424
      ],
      "rmse": 0.004176033407364396
    },
    {
      "id": 1,
      "p1": [
        3.8970390341896115,
        -1.653281435327624
      ],
      "p2": [
        3.9260958571619504,
        -2.794689612579633
      ],
      "length": 1.1417779670579566,
      "direction": [
        0.025448750817272454,
        -0.9996761280934143
      ],
      "rmse": 0.0039173390993372794
    },
    {
      "id": 2,
      "p1": [
        3.8943003704866483,
        -1.6365433043484727
      ],
      "p2": [
        5.089441192550855,
        -1.5861789995225066
      ],
      "length": 1.1962015498087732,
      "direction": [
        0.9991132533259708,
        0.042103527481608075
      ],
      "rmse": 0.005204059364606314
    },
    {
      "id": 3,
      "p1": [
        -0.5880107295357397,
        1.8102765470930298
      ],
      "p2": [
        1.3769297237613374,
        1.8595383310086044
      ],
      "length": 1.9655578618697207,
      "direction": [
        0.9996858863396566,
        0.02506249491361483
      ],
      "rmse": 0.008472872718829154
    },
    {
      "id": 4,
      "p1": [
        -4.230644775569468,
        4.962629900959157
      ],
      "p2": [
        -3.338961265238246,
        4.997556106013964
      ],
      "length": 0.8923672575773616,
      "direction": [
        0.9992337826817096,
        0.03913882401915093
      ],
      "rmse": 0.004261366926100085
    }
  ],
  "metadata": {
    "input_file": "/home/qzl/test_road/test_online_road/extracted_lidar_data_code/extracted_lidar_data/laserscan_json2/laserscan_000826.json",
    "num_walls": 5,
    "x_limit": 10.0,
    "y_limit": 5.0,
    "params": {
      "rdp_epsilon": 0.05,
      "wall_rmse_thresh": 0.07,
      "min_wall_length": 0.8,
      "gap_thresh": 2
    }
  }
}