{
  "walls": [
    {
      "id": 0,
      "p1": [
        -8.365855675690245,
        -0.03651500764252069
      ],
      "p2": [
        -8.334690648543964,
        -1.2821295402864634
      ],
      "length": 1.2460043430304792,
      "direction": [
        0.025011973128803492,
        -0.9996871516620608
      ],
      "rmse": 0.0021960126419099633
    },
    {
      "id": 1,
      "p1": [
        -2.7135108250175417,
        -1.304843634448938
      ],
      "p2": [
        -1.8666929195169595,
        -1.2903371285755425
      ],
      "length": 0.8469421490214357,
      "direction": [
        0.9998533034141187,
        0.017128095337021504
      ],
      "rmse": 0.0037317815849315546
    },
    {
      "id": 2,
      "p1": [
        0.15433206638461683,
        -1.1696256892580421
      ],
      "p2": [
        5.521279533025118,
        -1.036194554252575
      ],
      "length": 5.368605869075112,
      "direction": [
        0.9996910925330669,
        0.02485396362842349
      ],
      "rmse": 0.002830274833558605
    },
    {
      "id": 3,
      "p1": [
        7.2526135470783855,
        1.6404932144020339
      ],
      "p2": [
        7.26919130447174,
        0.3165658182810225
      ],
      "length": 1.3240311825028723,
      "direction": [
        0.012520669915039064,
        -0.9999216133392052
      ],
      "rmse": 0.00577680477083215
    },
    {
      "id": 4,
      "p1": [
        0.16386333236267525,
        1.1594665567870708
      ],
      "p2": [
        5.567559463370488,
        1.3356197126275056
      ],
      "length": 5.406566545468699,
      "direction": [
        0.9994690873695625,
        0.03258133500417091
      ],
      "rmse": 0.040652504720436244
    }
  ],
  "metadata": {
    "input_file": "/home/qzl/test_road/test_online_road/extracted_lidar_data_code/extracted_lidar_data/laserscan_json2/laserscan_000068.json",
    "num_walls": 5,
    "x_limit": 10.0,
    "y_limit": 5.0,
    "params": {
      "rdp_epsilon": 0.05,
      "wall_rmse_thresh": 0.07,
      "min_wall_length": 0.8,
      "gap_thresh": 2
    }
  }
}